Antonina/Antonina.py
Antonina/__init__.py
Antonina/__version__.py
Antonina/core.py
Antonina1-1.0.6.dist-info/LICENSE
Antonina1-1.0.6.dist-info/METADATA
Antonina1-1.0.6.dist-info/WHEEL
Antonina1-1.0.6.dist-info/top_level.txt
Antonina1-1.0.6.dist-info/RECORD
