Metadata-Version: 2.1
Name: Antonina1
Version: 1.0.6
Summary: 安冬妮娜助手1.0.6版本，用于显示具有安冬妮娜图片的提示弹窗，采用网页链接形式避开路径问题
Home-page: https://github.com/Jinqk/Antonina.git
Author: Jinqk
Author-email: jinqk@mail2.sysu.edu.cn
License: MIT
Classifier: License :: OSI Approved :: MIT License
Classifier: Programming Language :: Python
Classifier: Programming Language :: Python :: 3
Classifier: Programming Language :: Python :: 3.6
Classifier: Programming Language :: Python :: Implementation :: CPython
Classifier: Programming Language :: Python :: Implementation :: PyPy
Requires-Python: >=3.6.0
License-File: LICENSE
Requires-Dist: PySimpleGUI
Requires-Dist: pillow
Requires-Dist: requests
